miscset/__init__.py
miscset/dt.py
miscset/io.py
miscset/sh.py
miscset/version.py
miscset-0.1.0.dist-info/LICENSE
miscset-0.1.0.dist-info/METADATA
miscset-0.1.0.dist-info/WHEEL
miscset-0.1.0.dist-info/top_level.txt
miscset-0.1.0.dist-info/RECORD
