Metadata-Version: 2.1
Name: miscset
Version: 0.1.0
Summary: Miscellaneous python methods.
Home-page: https://github.com/setempler/miscset.py
Author: Sven Templer
Author-email: sven.templer@gmail.com
License: UNKNOWN
Platform: UNKNOWN
Classifier: Development Status :: 4 - Beta
Classifier: License :: OSI Approved :: MIT License
Classifier: Operating System :: MacOS
Classifier: Operating System :: POSIX :: Linux
Classifier: Programming Language :: Python :: 3
Classifier: Topic :: System :: Shells
Classifier: Topic :: Utilities
Classifier: Topic :: Text Processing :: Markup :: HTML
Requires-Python: >=3.6
License-File: LICENSE
Requires-Dist: pyyaml
